{
  "$schema": "https://turbo.build/schema.json",
  "pipeline": {
    "build": {
      "dependsOn": ["^build"],
      "outputs": ["dist/**", ".next/**", "build/**"],
      "cache": true
    },
    "dev": {
      "cache": false,
      "persistent": true
    },
    "lint": {
      "dependsOn": [],
      "cache": true
    },
    "typecheck": {
      "dependsOn": [],
      "cache": true
    },
    "test": {
      "dependsOn": [],
      "cache": true,
      "outputs": ["coverage/**"]
    },
    "db:generate": {
      "cache": false
    },
    "db:push": {
      "cache": false
    },
    "flutter:build": {
      "dependsOn": [],
      "cache": true,
      "outputs": ["build/web/**"]
    }
  },
  "globalEnv": [
    "NEXT_PUBLIC_SUPABASE_URL",
    "NEXT_PUBLIC_SUPABASE_PUBLISHABLE_KEY",
    "NEXT_PUBLIC_API_GATEWAY",
    "NEXT_PUBLIC_STRIPE_PUBLISHABLE_KEY",
    "NEXT_PUBLIC_GAMER_API_URL",
    "NEXT_PUBLIC_CATTLEYA_API_URL"
  ]
}